comics_ocr/__init__.py
comics_ocr/comics_ocr.py
comics_ocr/text_extractor.py
comics_ocr/mmocr/__init__.py
comics_ocr/mmocr/version.py
comics_ocr/mmocr/apis/__init__.py
comics_ocr/mmocr/apis/inference.py
comics_ocr/mmocr/apis/test.py
comics_ocr/mmocr/apis/train.py
comics_ocr/mmocr/apis/utils.py
comics_ocr/mmocr/core/__init__.py
comics_ocr/mmocr/core/mask.py
comics_ocr/mmocr/core/visualize.py
comics_ocr/mmocr/core/deployment/__init__.py
comics_ocr/mmocr/core/deployment/deploy_utils.py
comics_ocr/mmocr/core/evaluation/__init__.py
comics_ocr/mmocr/core/evaluation/hmean.py
comics_ocr/mmocr/core/evaluation/hmean_ic13.py
comics_ocr/mmocr/core/evaluation/hmean_iou.py
comics_ocr/mmocr/core/evaluation/kie_metric.py
comics_ocr/mmocr/core/evaluation/ner_metric.py
comics_ocr/mmocr/core/evaluation/ocr_metric.py
comics_ocr/mmocr/core/evaluation/utils.py
comics_ocr/mmocr/datasets/__init__.py
comics_ocr/mmocr/datasets/base_dataset.py
comics_ocr/mmocr/datasets/builder.py
comics_ocr/mmocr/datasets/icdar_dataset.py
comics_ocr/mmocr/datasets/kie_dataset.py
comics_ocr/mmocr/datasets/ner_dataset.py
comics_ocr/mmocr/datasets/ocr_dataset.py
comics_ocr/mmocr/datasets/ocr_seg_dataset.py
comics_ocr/mmocr/datasets/openset_kie_dataset.py
comics_ocr/mmocr/datasets/text_det_dataset.py
comics_ocr/mmocr/datasets/uniform_concat_dataset.py
comics_ocr/mmocr/datasets/pipelines/__init__.py
comics_ocr/mmocr/datasets/pipelines/box_utils.py
comics_ocr/mmocr/datasets/pipelines/crop.py
comics_ocr/mmocr/datasets/pipelines/custom_format_bundle.py
comics_ocr/mmocr/datasets/pipelines/dbnet_transforms.py
comics_ocr/mmocr/datasets/pipelines/kie_transforms.py
comics_ocr/mmocr/datasets/pipelines/loading.py
comics_ocr/mmocr/datasets/pipelines/ner_transforms.py
comics_ocr/mmocr/datasets/pipelines/ocr_seg_targets.py
comics_ocr/mmocr/datasets/pipelines/ocr_transforms.py
comics_ocr/mmocr/datasets/pipelines/test_time_aug.py
comics_ocr/mmocr/datasets/pipelines/transform_wrappers.py
comics_ocr-0.1.2.dist-info/LICENSE
comics_ocr-0.1.2.dist-info/METADATA
comics_ocr-0.1.2.dist-info/WHEEL
comics_ocr-0.1.2.dist-info/top_level.txt
comics_ocr-0.1.2.dist-info/RECORD
